conspira/__init__.py
conspira/detector.py
conspira-0.1.6.dist-info/LICENSE.txt
conspira-0.1.6.dist-info/METADATA
conspira-0.1.6.dist-info/WHEEL
conspira-0.1.6.dist-info/top_level.txt
conspira-0.1.6.dist-info/RECORD
