Metadata-Version: 2.1
Name: conspira
Version: 0.1.6
Summary: This is a package for conspiratory theory content identification.
Home-page: UNKNOWN
Author: Meng Xiao
Author-email: UNKNOWN
License: UNKNOWN
Platform: UNKNOWN
Requires-Dist: jieba
Requires-Dist: scikit-learn
Requires-Dist: requests
